{
  "version": "1.0.0",
  "stateHandle": "029ZAB",
  "expiresAt": "2021-05-21T14:46:37.000Z",
  "intent": "LOGIN",
  "remediation": {
    "type": "array",
    "value": [
      {
        "rel": [
          "create-form"
        ],
        "name": "enroll-authenticator",
        "relatesTo": [
          "$.currentAuthenticator"
        ],
        "href": "https://foo.oktapreview.com/idp/idx/challenge/answer",
        "method": "POST",
        "produces": "application/ion+json; okta-version=1.0.0",
        "value": [
          {
            "name": "credentials",
            "type": "object",
            "form": {
              "value": [
                {
                  "name": "passcode",
                  "label": "Enter password",
                  "secret": true
                }
              ]
            },
            "required": true
          },
          {
            "name": "stateHandle",
            "required": true,
            "value": "029ZAB",
            "visible": false,
            "mutable": false
          }
        ],
        "accepts": "application/json; okta-version=1.0.0"
      },
      {
        "rel": [
          "create-form"
        ],
        "name": "select-authenticator-enroll",
        "href": "https://foo.oktapreview.com/idp/idx/credential/enroll",
        "method": "POST",
        "produces": "application/ion+json; okta-version=1.0.0",
        "value": [
          {
            "name": "authenticator",
            "type": "object",
            "options": [
              {
                "label": "Password",
                "value": {
                  "form": {
                    "value": [
                      {
                        "name": "id",
                        "required": true,
                        "value": "autkx2th9yt4eRdhM5d6",
                        "mutable": false
                      },
                      {
                        "name": "methodType",
                        "required": false,
                        "value": "password",
                        "mutable": false
                      }
                    ]
                  }
                },
                "relatesTo": "$.authenticators.value[0]"
              }
            ]
          },
          {
            "name": "stateHandle",
            "required": true,
            "value": "029ZAB",
            "visible": false,
            "mutable": false
          }
        ],
        "accepts": "application/json; okta-version=1.0.0"
      }
    ]
  },
  "currentAuthenticator": {
    "type": "object",
    "value": {
      "type": "password",
      "key": "okta_password",
      "id": "autkx2th9yt4eRdhM5d6",
      "displayName": "Password",
      "methods": [
        {
          "type": "password"
        }
      ],
      "settings": {
        "complexity": {
          "minLength": 8,
          "minLowerCase": 0,
          "minUpperCase": 0,
          "minNumber": 0,
          "minSymbol": 0,
          "excludeUsername": false,
          "excludeAttributes": []
        },
        "age": {
          "minAgeMinutes": 0,
          "historyCount": 0
        }
      }
    }
  },
  "authenticators": {
    "type": "array",
    "value": [
      {
        "type": "password",
        "key": "okta_password",
        "id": "autkx2th9yt4eRdhM5d6",
        "displayName": "Password",
        "methods": [
          {
            "type": "password"
          }
        ]
      }
    ]
  },
  "authenticatorEnrollments": {
    "type": "array",
    "value": []
  },
  "enrollmentAuthenticator": {
    "type": "object",
    "value": {
      "type": "password",
      "key": "okta_password",
      "id": "autkx2th9yt4eRdhM5d6",
      "displayName": "Password",
      "methods": [
        {
          "type": "password"
        }
      ],
      "settings": {
        "complexity": {
          "minLength": 8,
          "minLowerCase": 0,
          "minUpperCase": 0,
          "minNumber": 0,
          "minSymbol": 0,
          "excludeUsername": false,
          "excludeAttributes": []
        },
        "age": {
          "minAgeMinutes": 0,
          "historyCount": 0
        }
      }
    }
  },
  "user": {
    "type": "object",
    "value": {
      "id": "00usib7f14C7d2nyY5d6"
    }
  },
  "cancel": {
    "rel": [
      "create-form"
    ],
    "name": "cancel",
    "href": "https://foo.oktapreview.com/idp/idx/cancel",
    "method": "POST",
    "produces": "application/ion+json; okta-version=1.0.0",
    "value": [
      {
        "name": "stateHandle",
        "required": true,
        "value": "029ZAB",
        "visible": false,
        "mutable": false
      }
    ],
    "accepts": "application/json; okta-version=1.0.0"
  },
  "app": {
    "type": "object",
    "value": {
      "name": "oidc_client",
      "label": "OIE Android Sample",
      "id": "0oal2s4yhspmifyt65d6"
    }
  }
}
